exiffield/__init__.py
exiffield/exceptions.py
exiffield/fields.py
exiffield/getters.py
exiffield/py.typed
django_exiffield-3.0.0.dist-info/LICENSE
django_exiffield-3.0.0.dist-info/WHEEL
django_exiffield-3.0.0.dist-info/METADATA
django_exiffield-3.0.0.dist-info/RECORD
